evoluteprompt/__init__.py
evoluteprompt/api.py
evoluteprompt/cli.py
evoluteprompt/core/__init__.py
evoluteprompt/core/database.py
evoluteprompt/core/prompt.py
evoluteprompt/core/provider.py
evoluteprompt/core/repository.py
evoluteprompt/core/response.py
evoluteprompt/core/strategy.py
evoluteprompt/core/template.py
evoluteprompt/core/types.py
evoluteprompt/integrations/__init__.py
evoluteprompt/integrations/anthropic/__init__.py
evoluteprompt/integrations/anthropic/provider.py
evoluteprompt/integrations/huggingface/__init__.py
evoluteprompt/integrations/huggingface/provider.py
evoluteprompt/integrations/openai/__init__.py
evoluteprompt/integrations/openai/provider.py
evoluteprompt/prompt_filters/__init__.py
evoluteprompt/prompt_filters/base.py
evoluteprompt/prompt_filters/pipeline.py
evoluteprompt/prompt_filters/safety.py
evoluteprompt/ui/__init__.py
evoluteprompt/ui/streamlit_app.py
evoluteprompt/utils/__init__.py
evoluteprompt/utils/cache.py
evoluteprompt/utils/hashing.py
evoluteprompt-0.1.2.dist-info/LICENSE
evoluteprompt-0.1.2.dist-info/METADATA
evoluteprompt-0.1.2.dist-info/WHEEL
evoluteprompt-0.1.2.dist-info/RECORD
