Metadata-Version: 2.1
Name: EvolutePrompt
Version: 0.1.2
Summary: LLM Prompt Manager
License: MIT
Author: ck46
Author-email: prof.chakas@gmail.com
Requires-Python: >=3.12,<4.0
Classifier: License :: OSI Approved :: MIT License
Classifier: Programming Language :: Python :: 3
Classifier: Programming Language :: Python :: 3.12
Requires-Dist: aiohttp (>=3.9.3,<4.0.0)
Requires-Dist: aiosqlite (>=0.21.0,<0.22.0)
Requires-Dist: autopep8 (>=2.3.2,<3.0.0)
Requires-Dist: better-profanity (>=0.7.0,<0.8.0)
Requires-Dist: fastapi (>=0.115.11,<0.116.0)
Requires-Dist: jinja2 (>=3.1.6,<4.0.0)
Requires-Dist: pydantic (>=2.10.6,<3.0.0)
Requires-Dist: pytest (>=8.3.5,<9.0.0)
Requires-Dist: semver (>=3.0.4,<4.0.0)
Requires-Dist: streamlit (>=1.43.2,<2.0.0)
Requires-Dist: tiktoken (>=0.9.0,<0.10.0)
Requires-Dist: tortoise-orm (>=0.24.2,<0.25.0)
Requires-Dist: uvicorn (>=0.34.0,<0.35.0)
